{
  "_id": "6876c884c631ebdf1e949dd2",
  "content_hash": "086e2cf3f7d20f014a7f9aa4ff537390",
  "collected_at": "2025-07-15T22:19:29.118724",
  "content": "WAEC Past Questions\n \nand Answers on Biology\n \n \n\u200b \n \n \n 2016 WAEC Past\n \nQuestions\n \n \nQ\nu\ne\ns\nt\ni\no\nn\n \n1\n \n \nIn evolution, analogous structures are significant because they\n \nshow\n \n \nO\np\nt\ni\no\nn\ns\n \n \nA) physiological\n \ndiversity\n \n \nB) functional\n \ndiversity\n \n \nC) genetic",
  "file_info": {
    "filename": "WAEC-BIOLOGY-EXAMPULSE.pdf",
    "filepath": "data-preparation/pdf_documents/WAEC-BIOLOGY-EXAMPULSE.pdf",
    "page_number": 1,
    "total_pages": 82,
    "file_size": 6173539
  },
  "metadata": {
    "producer": "iLovePDF",
    "creator": "PyPDF",
    "creationdate": "",
    "moddate": "2023-02-14T12:06:14+01:00",
    "source": "data-preparation/pdf_documents/WAEC-BIOLOGY-EXAMPULSE.pdf",
    "total_pages": 82,
    "page": 0,
    "page_label": "1"
  },
  "source": "WAEC-BIOLOGY-EXAMPULSE.pdf#page=1",
  "type": "pdf",
  "year": null
}