{
  "_id": "6876c885c631ebdf1e949df8",
  "content_hash": "3fe15c180c58a76f85fac9b3ba9feb57",
  "collected_at": "2025-07-15T22:19:29.119767",
  "content": "Question 9\n \n \nIn which of the following habitats is paramecium not found?\n \n \nOption\ns\n \n \nA)\n \nPond\n \n \nB)\n \nAquarium\n \n \nC)\n \nLake\n \n \nD) Puddle\n \n \nThe correct answer is",
  "file_info": {
    "filename": "WAEC-BIOLOGY-EXAMPULSE.pdf",
    "filepath": "data-preparation/pdf_documents/WAEC-BIOLOGY-EXAMPULSE.pdf",
    "page_number": 24,
    "total_pages": 82,
    "file_size": 6173539
  },
  "metadata": {
    "producer": "iLovePDF",
    "creator": "PyPDF",
    "creationdate": "",
    "moddate": "2023-02-14T12:06:14+01:00",
    "source": "data-preparation/pdf_documents/WAEC-BIOLOGY-EXAMPULSE.pdf",
    "total_pages": 82,
    "page": 23,
    "page_label": "24"
  },
  "source": "WAEC-BIOLOGY-EXAMPULSE.pdf#page=24",
  "type": "pdf",
  "year": null
}